pyAbacus/__init__.py
pyAbacus/constants.py
pyAbacus/core.py
pyAbacus/exceptions.py
pyAbacus-1.2.1.dist-info/LICENSE
pyAbacus-1.2.1.dist-info/METADATA
pyAbacus-1.2.1.dist-info/WHEEL
pyAbacus-1.2.1.dist-info/top_level.txt
pyAbacus-1.2.1.dist-info/RECORD
