Metadata-Version: 2.1
Name: pyAbacus
Version: 1.2.1
Summary: Built to use with Tausand Abacus coincidence counters
Home-page: https://github.com/Tausand-dev/PyAbacus
Author: Juan Barbosa
Author-email: js.barbosa10@uniandes.edu.co
Maintainer: David Guzman
Maintainer-email: da.guzman@outlook.com
License: GPL
Project-URL: Bug Tracker, https://github.com/Tausand-dev/PyAbacus/issues
Classifier: Development Status :: 5 - Production/Stable
Classifier: Topic :: Utilities
Classifier: License :: OSI Approved :: GNU General Public License (GPL)
Classifier: Operating System :: OS Independent
Classifier: Programming Language :: Python :: 3
Requires-Python: >=3.6
License-File: LICENSE
Requires-Dist: pyserial
